gplib/__init__.py
gplib/gaussian_process.py
gplib/multivariate_gaussian.py
gplib/plot.py
gplib/covariance_functions/__init__.py
gplib/covariance_functions/covariance_function.py
gplib/covariance_functions/kernel_based.py
gplib/covariance_functions/posterior.py
gplib/data_manipulations/__init__.py
gplib/data_manipulations/cross.py
gplib/data_manipulations/data_transformations.py
gplib/data_manipulations/full.py
gplib/data_manipulations/rand_fold.py
gplib/data_manipulations/unfold.py
gplib/data_manipulations/validation.py
gplib/fitting_methods/__init__.py
gplib/fitting_methods/fitting_method.py
gplib/fitting_methods/grid_search.py
gplib/fitting_methods/local_search.py
gplib/fitting_methods/multi_start.py
gplib/kernel_functions/__init__.py
gplib/kernel_functions/constant.py
gplib/kernel_functions/dot_product_function.py
gplib/kernel_functions/exponential.py
gplib/kernel_functions/gamma_exponential15.py
gplib/kernel_functions/kernel_function.py
gplib/kernel_functions/linear.py
gplib/kernel_functions/matern32.py
gplib/kernel_functions/matern52.py
gplib/kernel_functions/periodic.py
gplib/kernel_functions/product.py
gplib/kernel_functions/rational_quadratic.py
gplib/kernel_functions/squared_exponential.py
gplib/kernel_functions/stationary_function.py
gplib/kernel_functions/sum.py
gplib/kernel_functions/white_noise.py
gplib/mean_functions/__init__.py
gplib/mean_functions/constant.py
gplib/mean_functions/fixed.py
gplib/mean_functions/mean_function.py
gplib/mean_functions/posterior.py
gplib/metrics/__init__.py
gplib/metrics/bic.py
gplib/metrics/lml.py
gplib/metrics/loocv.py
gplib/metrics/metric.py
gplib/metrics/pearsonr.py
gplib/metrics/predictive_density.py
gplib/metrics/rmse.py
gplib/parameters/__init__.py
gplib/parameters/log_parameter_transformation.py
gplib/parameters/none_parameter_transformation.py
gplib/parameters/parameter.py
gplib/parameters/parameter_transformation.py
gplib/parameters/parametrizable.py
gplib/parameters/with_parameters.py
gplib-0.17.3.dist-info/METADATA
gplib-0.17.3.dist-info/WHEEL
gplib-0.17.3.dist-info/licenses/LICENSE.txt
gplib-0.17.3.dist-info/RECORD
