Metadata-Version: 2.1
Name: gplib
Version: 0.17.3
Summary: Python library for Gaussian Process Regression.
Project-URL: repository, https://gitlab.com/ibaidev/gplib
Author-email: Ibai Roman <ibaidev@protonmail.com>
License:                     GNU GENERAL PUBLIC LICENSE
License-File: LICENSE.txt
Keywords: Gaussian Process
Classifier: Development Status :: 4 - Beta
Classifier: Environment :: Console
Classifier: Intended Audience :: Developers
Classifier: Intended Audience :: Science/Research
Classifier: License :: OSI Approved :: GNU General Public License v3 (GPLv3)
Classifier: Operating System :: POSIX
Classifier: Programming Language :: Python
Classifier: Topic :: Scientific/Engineering :: Artificial Intelligence
Requires-Python: >=3.8
Requires-Dist: matplotlib>=1.5.1
Requires-Dist: numpy>=1.11.0
Requires-Dist: scipy>=1.0.0
